fluidpythran/__init__.py
fluidpythran/_path_data_tests.py
fluidpythran/_version.py
fluidpythran/aheadoftime.py
fluidpythran/annotation.py
fluidpythran/compat.py
fluidpythran/config.py
fluidpythran/dist.py
fluidpythran/for_test_init.py
fluidpythran/for_test_justintime.py
fluidpythran/justintime.py
fluidpythran/log.py
fluidpythran/mpi.py
fluidpythran/pythranizer.py
fluidpythran/run.py
fluidpythran/test_dist.py
fluidpythran/test_init.py
fluidpythran/test_init_fluidpythranized.py
fluidpythran/test_justintime.py
fluidpythran/test_run.py
fluidpythran/test_util.py
fluidpythran/transpiler.py
fluidpythran/util.py
fluidpythran_cl/__init__.py
fluidpythran_cl/run_pythran.py
fluidpythran-0.1.7.dist-info/AUTHORS.rst
fluidpythran-0.1.7.dist-info/AUTHORS.rst~
fluidpythran-0.1.7.dist-info/LICENSE.txt
fluidpythran-0.1.7.dist-info/METADATA
fluidpythran-0.1.7.dist-info/WHEEL
fluidpythran-0.1.7.dist-info/entry_points.txt
fluidpythran-0.1.7.dist-info/top_level.txt
fluidpythran-0.1.7.dist-info/RECORD
