Metadata-Version: 2.1
Name: fluidpythran
Version: 0.1.7
Summary: Easily speedup your Python code with Pythran
Home-page: UNKNOWN
License: CeCILL-B License
Keywords: pythran
Platform: UNKNOWN
Classifier: Programming Language :: Python :: 3
Classifier: Programming Language :: Python :: 3.6
Requires-Dist: astunparse
Provides-Extra: dev
Requires-Dist: sphinx ; extra == 'dev'
Requires-Dist: sphinx-rtd-theme ; extra == 'dev'
Requires-Dist: numpydoc ; extra == 'dev'
Requires-Dist: ipython ; extra == 'dev'
Requires-Dist: jupyter ; extra == 'dev'
Requires-Dist: fluiddyn ; extra == 'dev'
Provides-Extra: test
Requires-Dist: pytest ; extra == 'test'
Requires-Dist: numpy ; extra == 'test'
Requires-Dist: pythran ; extra == 'test'
